outpostspawner/__init__.py
outpostspawner/_version.py
outpostspawner/api_flavors_update.py
outpostspawner/misc.py
outpostspawner/outpostspawner.py
jupyterhub_outpostspawner-2.1.0.dist-info/METADATA
jupyterhub_outpostspawner-2.1.0.dist-info/WHEEL
jupyterhub_outpostspawner-2.1.0.dist-info/licenses/LICENSE
jupyterhub_outpostspawner-2.1.0.dist-info/RECORD
