Metadata-Version: 2.4
Name: jupyterhub-outpostspawner
Version: 2.1.0
Summary: JupyterHub OutpostSpawner enables start on multiple, remote system
Author-email: Tim Kreuzer <t.kreuzer@fz-juelich.de>
License: BSD 3-Clause License
License-File: LICENSE
Keywords: jupyterhub,kubernetes,spawner
Requires-Python: >=3.9
Requires-Dist: escapism
Requires-Dist: jinja2
Requires-Dist: jupyterhub-forwardbasespawner>=2.0.0
Requires-Dist: jupyterhub>=5.0.0
Requires-Dist: kubernetes
Requires-Dist: traitlets
Requires-Dist: urllib3
